terratest/__init__.py
terratest/__main__.py
terratest/constants.py
terratest/cli/main.py
terratest/cli/commands/run.py
terratest/cli/commands/web.py
terratest/core/docker_manager.py
terratest/core/executor.py
terratest/core/image_manager.py
terratest/core/parser.py
terratest/core/ssh_handler.py
terratest/core/validation.py
terratest/utils/__init__.py
terratest/utils/config_store.py
terratest/utils/filesystem.py
terratest/utils/logging.py
terratest/web/app.py
terratest/web/routes/docker_image.py
terratest/web/routes/filesystem.py
terratest/web/routes/job_file_read.py
terratest/web/routes/job_files.py
terratest/web/routes/jobs.py
terratest/web/routes/jobs_delete.py
terratest/web/routes/jobs_list.py
terratest/web/static/index.html
terratest/web/static/css/styles.css
terratest/web/static/js/app.js
terratest-0.1.1.dist-info/licenses/LICENSE
terratest-0.1.1.dist-info/METADATA
terratest-0.1.1.dist-info/WHEEL
terratest-0.1.1.dist-info/entry_points.txt
terratest-0.1.1.dist-info/top_level.txt
terratest-0.1.1.dist-info/RECORD
