Metadata-Version: 2.4
Name: terratest
Version: 0.1.1
Summary: Terratest Web UI - Interfaz web para ejecutar y gestionar tests de Terraform en contenedores Docker
Author-email: Yorlin <yorlin@example.com>
License-Expression: MIT
Project-URL: Homepage, https://github.com/yourusername/terratest
Project-URL: Repository, https://github.com/yourusername/terratest
Project-URL: Documentation, https://github.com/yourusername/terratest#readme
Project-URL: Issues, https://github.com/yourusername/terratest/issues
Keywords: terraform,testing,docker,web-ui,infrastructure
Classifier: Development Status :: 4 - Beta
Classifier: Intended Audience :: Developers
Classifier: Topic :: Software Development :: Testing
Classifier: Topic :: System :: Systems Administration
Classifier: Programming Language :: Python :: 3
Classifier: Programming Language :: Python :: 3.12
Requires-Python: >=3.12
License-File: LICENSE
Requires-Dist: typer<0.21.0,>=0.20.0
Requires-Dist: rich<15.0.0,>=14.2.0
Requires-Dist: fastapi<0.124.0,>=0.123.5
Requires-Dist: uvicorn<0.39.0,>=0.38.0
Requires-Dist: pydantic<3.0.0,>=2.12.5
Requires-Dist: docker<8.0.0,>=7.1.0
Requires-Dist: cryptography<47.0.0,>=46.0.3
Provides-Extra: dev
Requires-Dist: pytest>=7.0.0; extra == "dev"
Requires-Dist: pytest-cov>=4.0.0; extra == "dev"
Requires-Dist: black>=23.0.0; extra == "dev"
Requires-Dist: ruff>=0.1.1; extra == "dev"
Dynamic: license-file
